coronado/__init__.py
coronado/address.py
coronado/auth.py
coronado/baseobjects.py
coronado/cardaccount.py
coronado/cardprog.py
coronado/config.py
coronado/daterange.py
coronado/exceptions.py
coronado/healthmonitor.py
coronado/merchant.py
coronado/merchantcodes.py
coronado/offer.py
coronado/publisher.py
coronado/reward.py
coronado/selfie.py
coronado/strictaddress.py
coronado/todo.py
coronado/tools.py
coronado/transaction.py
coronado-1.3.47.dist-info/LICENSE
coronado-1.3.47.dist-info/METADATA
coronado-1.3.47.dist-info/WHEEL
coronado-1.3.47.dist-info/entry_points.txt
coronado-1.3.47.dist-info/top_level.txt
coronado-1.3.47.dist-info/RECORD
