Metadata-Version: 2.1
Name: coronado
Version: 1.3.47
Summary: Coronado - Triple API Python wrapper and reference implementation.
Author-email: Eugene Ciurana pr3d4t0r <eugene.ciurana@numo.com>
Classifier: Intended Audience :: Other Audience
Classifier: Operating System :: MacOS
Classifier: Operating System :: Unix
Classifier: Programming Language :: Python :: 3
Classifier: Programming Language :: Python :: 3.9
Requires-Python: >=3.9.9
License-File: LICENSE
Requires-Dist: appdirs
Requires-Dist: google-i18n-address
Requires-Dist: iso18245
Requires-Dist: python-jose
Requires-Dist: requests
